aind_registration_utils/__init__.py
aind_registration_utils/annotations.py
aind_registration_utils/ants.py
aind_registration_utils/domains.py
aind_registration_utils/image_utils.py
aind_registration_utils/py.typed
aind_registration_utils/recipes.py
aind_registration_utils/types.py
aind_registration_utils/utils.py
aind_registration_utils/vtk.py
aind_registration_utils/scripts/register_individual_to_template.py
aind_registration_utils-0.4.1.dist-info/licenses/LICENSE
aind_registration_utils-0.4.1.dist-info/METADATA
aind_registration_utils-0.4.1.dist-info/WHEEL
aind_registration_utils-0.4.1.dist-info/entry_points.txt
aind_registration_utils-0.4.1.dist-info/top_level.txt
aind_registration_utils-0.4.1.dist-info/RECORD
