Metadata-Version: 2.4
Name: aind-registration-utils
Version: 0.4.1
Summary: Tools for registration of individual brains to a template brain
Author: Allen Institute for Neural Dynamics
Author-email: Galen Lynch <galen@galenlynch.com>
License-Expression: MIT
Project-URL: Repository, https://github.com/AllenNeuralDynamics/aind-registration-utils/
Project-URL: Issues, https://github.com/AllenNeuralDynamics/aind-registration-utils/issues
Project-URL: Changelog, https://github.com/AllenNeuralDynamics/aind-registration-utils/blob/main/CHANGELOG.md
Classifier: Programming Language :: Python :: 3
Requires-Python: >=3.10
License-File: LICENSE
Requires-Dist: aind-anatomical-utils<0.5,>=0.1
Requires-Dist: aind-ants-transform-sidecar<0.2,>=0.1
Requires-Dist: antspyx<0.7,>=0.2
Requires-Dist: numpy<3,>=1
Requires-Dist: pandas<3,>=2
Requires-Dist: scikit-image<1,>=0.14
Requires-Dist: scipy<2,>=1
Requires-Dist: SimpleITK<3,>=2
Requires-Dist: vtk<10,>=9
Dynamic: license-file
